arcade_mongodb/__init__.py
arcade_mongodb/database_engine.py
arcade_mongodb/tools/__init__.py
arcade_mongodb/tools/mongodb.py
arcade_mongodb/tools/utils.py
arcade_mongodb-0.1.1.dist-info/METADATA
arcade_mongodb-0.1.1.dist-info/WHEEL
arcade_mongodb-0.1.1.dist-info/RECORD
